{
    "champid": "sauron",
    "data": {
        "2+1": {
            "rank": 1,
            "prestige": "279",
            "hp": "Offensive: Damage Over Time",
            "attack": "99",
            "crit_rate": "478",
            "crit_dmge": "563",
            "armor": "33",
            "block_prof": "2845",
            "energy_resist": "0",
            "physical_resist": "0",
            "crit_resist": "0",
            "sig_info": [
                "After the start of the fight, if the Opponent attempts to inflict a Bleed, or Incinerate effect while a Degeneration Passive is active, inflict the Opponent with a Passive version of that effect dealing +297 damage over 2 seconds.",
                "Increase personal Prowess Passive Potency by a flat 1.77 to 7.77%."
            ],
            "url_page": "https://auntm.ai/champions/sauron/tier/2",
            "champid": "sauron+2+1",
            "challenger_rating": 20,
            "abilities": {
                "ALWAYS ACTIVE": [
                    "Immune to all Power Steal, Poison, and Sauron's Regeneration Rate cannot be decreased or increased by outside sources.",
                    "Take -95% less damage from Bleed effects and gain +25% Critical Resistance while Bleeding.",
                    "When Sauron is struck, 30% chance to gain a Regen Passive healing 10% of the damage taken per personal Prowess Passive effect he has.",
                    "Light Attacks have 35% chance to deal 50% of the damage dealt as a burst of Physical Damage. This ability can also trigger through block."
                ],
                "PROWESS (MAX: 10)": [
                    "Each time one of Sauron\u2019s Abilities fails to trigger due to chance gain a 10% Prowess Passive. Gain an additional 2 Prowess Passive if Sauron's Ability fails due to Ability Accuracy modification.",
                    "At 7 Prowess Passives, Dash Attacks, Heavy and Special Attacks grant an Unblockable Passive for 4 seconds. This Unblockable Passive is paused during Special Attacks and has a 10 second cooldown unless Sauron's Ability Accuracy is being modified or Sauron is affected by a Degeneration.",
                    "At 10 Prowess Passives, Dashing Attacks, inflict a Bleed Passive, dealing +74.25 damage over 4 seconds. This ability can also trigger through block.",
                    "Landing the first hit of a Heavy Attack will consume 3 Prowess Passives and gain a Fury Passive, granting +49.5 Attack Rating for 4 seconds"
                ],
                "ALL SPECIAL ATTACKS": [
                    "All Prowess Passives are removed at the end of Special Attacks.",
                    "On activation, pause the Degeneration Passive from Extinction Mode for 8 seconds."
                ],
                "EXTINCTION MODE": [
                    "While at 10 Prowess Passives, when you hit the Opponent, inflict a Degeneration Passive, dealing +39.6 direct damage over 5 seconds.",
                    "Increase Physical Burst Potency by 50% and all personal Abilities have 100% Ability Accuracy.",
                    "If the Degeneration Passive from Extinction Mode expires, remove all Prowess Passives."
                ],
                "SPECIAL ATTACK 1": [
                    "After this Special Attack ends, for each physical burst hit dealt to the Opponent, heal for 25% the damage dealt for 10 seconds."
                ],
                "SPECIAL ATTACK 2": [
                    "After this Special Attack ends, increase the Potency of all personal burst Physical Damage by 100% for 10 seconds."
                ],
                "SPECIAL ATTACK 3": [
                    "After this Special Attack ends, inflict a Degeneration Passive, dealing +24.75 direct damage over 5 seconds per personal Passive effect that has expired on Sauron or on the Opponent. (capped at 30) Reset after Special 3 activation."
                ]
            }
        },
        "2+2": {
            "rank": 2,
            "prestige": "370",
            "hp": "Offensive: Damage Over Time",
            "attack": "130",
            "crit_rate": "493",
            "crit_dmge": "580",
            "armor": "52",
            "block_prof": "2934",
            "energy_resist": "0",
            "physical_resist": "0",
            "crit_resist": "0",
            "sig_info": [
                "After the start of the fight, if the Opponent attempts to inflict a Bleed, or Incinerate effect while a Degeneration Passive is active, inflict the Opponent with a Passive version of that effect dealing +390 damage over 2 seconds.",
                "Increase personal Prowess Passive Potency by a flat 1.77 to 7.77%."
            ],
            "url_page": "https://auntm.ai/champions/sauron/tier/2",
            "champid": "sauron+2+2",
            "challenger_rating": 30,
            "abilities": {
                "ALWAYS ACTIVE": [
                    "Immune to all Power Steal, Poison, and Sauron's Regeneration Rate cannot be decreased or increased by outside sources.",
                    "Take -95% less damage from Bleed effects and gain +25% Critical Resistance while Bleeding.",
                    "When Sauron is struck, 30% chance to gain a Regen Passive healing 10% of the damage taken per personal Prowess Passive effect he has.",
                    "Light Attacks have 35% chance to deal 50% of the damage dealt as a burst of Physical Damage. This ability can also trigger through block."
                ],
                "PROWESS (MAX: 10)": [
                    "Each time one of Sauron\u2019s Abilities fails to trigger due to chance gain a 10% Prowess Passive. Gain an additional 2 Prowess Passive if Sauron's Ability fails due to Ability Accuracy modification.",
                    "At 7 Prowess Passives, Dash Attacks, Heavy and Special Attacks grant an Unblockable Passive for 4 seconds. This Unblockable Passive is paused during Special Attacks and has a 10 second cooldown unless Sauron's Ability Accuracy is being modified or Sauron is affected by a Degeneration.",
                    "At 10 Prowess Passives, Dashing Attacks, inflict a Bleed Passive, dealing +97.5 damage over 4 seconds. This ability can also trigger through block.",
                    "Landing the first hit of a Heavy Attack will consume 3 Prowess Passives and gain a Fury Passive, granting +65 Attack Rating for 4 seconds"
                ],
                "ALL SPECIAL ATTACKS": [
                    "All Prowess Passives are removed at the end of Special Attacks.",
                    "On activation, pause the Degeneration Passive from Extinction Mode for 8 seconds."
                ],
                "EXTINCTION MODE": [
                    "While at 10 Prowess Passives, when you hit the Opponent, inflict a Degeneration Passive, dealing +52 direct damage over 5 seconds.",
                    "Increase Physical Burst Potency by 50% and all personal Abilities have 100% Ability Accuracy.",
                    "If the Degeneration Passive from Extinction Mode expires, remove all Prowess Passives."
                ],
                "SPECIAL ATTACK 1": [
                    "After this Special Attack ends, for each physical burst hit dealt to the Opponent, heal for 25% the damage dealt for 10 seconds."
                ],
                "SPECIAL ATTACK 2": [
                    "After this Special Attack ends, increase the Potency of all personal burst Physical Damage by 100% for 10 seconds."
                ],
                "SPECIAL ATTACK 3": [
                    "After this Special Attack ends, inflict a Degeneration Passive, dealing +32.5 direct damage over 5 seconds per personal Passive effect that has expired on Sauron or on the Opponent. (capped at 30) Reset after Special 3 activation."
                ]
            }
        },
        "2+3": {
            "rank": 3,
            "prestige": "585",
            "hp": "Offensive: Damage Over Time",
            "attack": "206",
            "crit_rate": "508",
            "crit_dmge": "598",
            "armor": "71",
            "block_prof": "3023",
            "energy_resist": "0",
            "physical_resist": "0",
            "crit_resist": "0",
            "sig_info": [
                "After the start of the fight, if the Opponent attempts to inflict a Bleed, or Incinerate effect while a Degeneration Passive is active, inflict the Opponent with a Passive version of that effect dealing +618 damage over 2 seconds.",
                "Increase personal Prowess Passive Potency by a flat 1.77 to 7.77%."
            ],
            "url_page": "https://auntm.ai/champions/sauron/tier/2",
            "champid": "sauron+2+3",
            "challenger_rating": 40,
            "abilities": {
                "ALWAYS ACTIVE": [
                    "Immune to all Power Steal, Poison, and Sauron's Regeneration Rate cannot be decreased or increased by outside sources.",
                    "Take -95% less damage from Bleed effects and gain +25% Critical Resistance while Bleeding.",
                    "When Sauron is struck, 30% chance to gain a Regen Passive healing 10% of the damage taken per personal Prowess Passive effect he has.",
                    "Light Attacks have 35% chance to deal 50% of the damage dealt as a burst of Physical Damage. This ability can also trigger through block."
                ],
                "PROWESS (MAX: 10)": [
                    "Each time one of Sauron\u2019s Abilities fails to trigger due to chance gain a 10% Prowess Passive. Gain an additional 2 Prowess Passive if Sauron's Ability fails due to Ability Accuracy modification.",
                    "At 7 Prowess Passives, Dash Attacks, Heavy and Special Attacks grant an Unblockable Passive for 4 seconds. This Unblockable Passive is paused during Special Attacks and has a 10 second cooldown unless Sauron's Ability Accuracy is being modified or Sauron is affected by a Degeneration.",
                    "At 10 Prowess Passives, Dashing Attacks, inflict a Bleed Passive, dealing +154.5 damage over 4 seconds. This ability can also trigger through block.",
                    "Landing the first hit of a Heavy Attack will consume 3 Prowess Passives and gain a Fury Passive, granting +103 Attack Rating for 4 seconds"
                ],
                "ALL SPECIAL ATTACKS": [
                    "All Prowess Passives are removed at the end of Special Attacks.",
                    "On activation, pause the Degeneration Passive from Extinction Mode for 8 seconds."
                ],
                "EXTINCTION MODE": [
                    "While at 10 Prowess Passives, when you hit the Opponent, inflict a Degeneration Passive, dealing +82.4 direct damage over 5 seconds.",
                    "Increase Physical Burst Potency by 50% and all personal Abilities have 100% Ability Accuracy.",
                    "If the Degeneration Passive from Extinction Mode expires, remove all Prowess Passives."
                ],
                "SPECIAL ATTACK 1": [
                    "After this Special Attack ends, for each physical burst hit dealt to the Opponent, heal for 25% the damage dealt for 10 seconds."
                ],
                "SPECIAL ATTACK 2": [
                    "After this Special Attack ends, increase the Potency of all personal burst Physical Damage by 100% for 10 seconds."
                ],
                "SPECIAL ATTACK 3": [
                    "After this Special Attack ends, inflict a Degeneration Passive, dealing +51.5 direct damage over 5 seconds per personal Passive effect that has expired on Sauron or on the Opponent. (capped at 30) Reset after Special 3 activation."
                ]
            }
        },
        "3+1": {
            "rank": 1,
            "prestige": "507",
            "hp": "Offensive: Damage Over Time",
            "attack": "179",
            "crit_rate": "508",
            "crit_dmge": "598",
            "armor": "71",
            "block_prof": "3023",
            "energy_resist": "0",
            "physical_resist": "0",
            "crit_resist": "0",
            "sig_info": [
                "After the start of the fight, if the Opponent attempts to inflict a Bleed, or Incinerate effect while a Degeneration Passive is active, inflict the Opponent with a Passive version of that effect dealing +537 damage over 2 seconds.",
                "Increase personal Prowess Passive Potency by a flat 1.77 to 7.77%."
            ],
            "url_page": "https://auntm.ai/champions/sauron/tier/3",
            "champid": "sauron+3+1",
            "challenger_rating": 40,
            "abilities": {
                "ALWAYS ACTIVE": [
                    "Immune to all Power Steal, Poison, and Sauron's Regeneration Rate cannot be decreased or increased by outside sources.",
                    "Take -95% less damage from Bleed effects and gain +25% Critical Resistance while Bleeding.",
                    "When Sauron is struck, 30% chance to gain a Regen Passive healing 10% of the damage taken per personal Prowess Passive effect he has.",
                    "Light Attacks have 35% chance to deal 50% of the damage dealt as a burst of Physical Damage. This ability can also trigger through block."
                ],
                "PROWESS (MAX: 10)": [
                    "Each time one of Sauron\u2019s Abilities fails to trigger due to chance gain a 10% Prowess Passive. Gain an additional 2 Prowess Passive if Sauron's Ability fails due to Ability Accuracy modification.",
                    "At 7 Prowess Passives, Dash Attacks, Heavy and Special Attacks grant an Unblockable Passive for 4 seconds. This Unblockable Passive is paused during Special Attacks and has a 10 second cooldown unless Sauron's Ability Accuracy is being modified or Sauron is affected by a Degeneration.",
                    "At 10 Prowess Passives, Dashing Attacks, inflict a Bleed Passive, dealing +134.25 damage over 4 seconds. This ability can also trigger through block.",
                    "Landing the first hit of a Heavy Attack will consume 3 Prowess Passives and gain a Fury Passive, granting +89.5 Attack Rating for 4 seconds"
                ],
                "ALL SPECIAL ATTACKS": [
                    "All Prowess Passives are removed at the end of Special Attacks.",
                    "On activation, pause the Degeneration Passive from Extinction Mode for 8 seconds."
                ],
                "EXTINCTION MODE": [
                    "While at 10 Prowess Passives, when you hit the Opponent, inflict a Degeneration Passive, dealing +71.6 direct damage over 5 seconds.",
                    "Increase Physical Burst Potency by 50% and all personal Abilities have 100% Ability Accuracy.",
                    "If the Degeneration Passive from Extinction Mode expires, remove all Prowess Passives."
                ],
                "SPECIAL ATTACK 1": [
                    "After this Special Attack ends, for each physical burst hit dealt to the Opponent, heal for 25% the damage dealt for 10 seconds."
                ],
                "SPECIAL ATTACK 2": [
                    "After this Special Attack ends, increase the Potency of all personal burst Physical Damage by 100% for 10 seconds."
                ],
                "SPECIAL ATTACK 3": [
                    "After this Special Attack ends, inflict a Degeneration Passive, dealing +44.75 direct damage over 5 seconds per personal Passive effect that has expired on Sauron or on the Opponent. (capped at 30) Reset after Special 3 activation."
                ]
            }
        },
        "3+2": {
            "rank": 2,
            "prestige": "808",
            "hp": "Offensive: Damage Over Time",
            "attack": "285",
            "crit_rate": "523",
            "crit_dmge": "615",
            "armor": "93",
            "block_prof": "3112",
            "energy_resist": "0",
            "physical_resist": "0",
            "crit_resist": "0",
            "sig_info": [
                "After the start of the fight, if the Opponent attempts to inflict a Bleed, or Incinerate effect while a Degeneration Passive is active, inflict the Opponent with a Passive version of that effect dealing +855 damage over 2 seconds.",
                "Increase personal Prowess Passive Potency by a flat 1.77 to 7.77%."
            ],
            "url_page": "https://auntm.ai/champions/sauron/tier/3",
            "champid": "sauron+3+2",
            "challenger_rating": 50,
            "abilities": {
                "ALWAYS ACTIVE": [
                    "Immune to all Power Steal, Poison, and Sauron's Regeneration Rate cannot be decreased or increased by outside sources.",
                    "Take -95% less damage from Bleed effects and gain +25% Critical Resistance while Bleeding.",
                    "When Sauron is struck, 30% chance to gain a Regen Passive healing 10% of the damage taken per personal Prowess Passive effect he has.",
                    "Light Attacks have 35% chance to deal 50% of the damage dealt as a burst of Physical Damage. This ability can also trigger through block."
                ],
                "PROWESS (MAX: 10)": [
                    "Each time one of Sauron\u2019s Abilities fails to trigger due to chance gain a 10% Prowess Passive. Gain an additional 2 Prowess Passive if Sauron's Ability fails due to Ability Accuracy modification.",
                    "At 7 Prowess Passives, Dash Attacks, Heavy and Special Attacks grant an Unblockable Passive for 4 seconds. This Unblockable Passive is paused during Special Attacks and has a 10 second cooldown unless Sauron's Ability Accuracy is being modified or Sauron is affected by a Degeneration.",
                    "At 10 Prowess Passives, Dashing Attacks, inflict a Bleed Passive, dealing +213.75 damage over 4 seconds. This ability can also trigger through block.",
                    "Landing the first hit of a Heavy Attack will consume 3 Prowess Passives and gain a Fury Passive, granting +142.5 Attack Rating for 4 seconds"
                ],
                "ALL SPECIAL ATTACKS": [
                    "All Prowess Passives are removed at the end of Special Attacks.",
                    "On activation, pause the Degeneration Passive from Extinction Mode for 8 seconds."
                ],
                "EXTINCTION MODE": [
                    "While at 10 Prowess Passives, when you hit the Opponent, inflict a Degeneration Passive, dealing +114 direct damage over 5 seconds.",
                    "Increase Physical Burst Potency by 50% and all personal Abilities have 100% Ability Accuracy.",
                    "If the Degeneration Passive from Extinction Mode expires, remove all Prowess Passives."
                ],
                "SPECIAL ATTACK 1": [
                    "After this Special Attack ends, for each physical burst hit dealt to the Opponent, heal for 25% the damage dealt for 10 seconds."
                ],
                "SPECIAL ATTACK 2": [
                    "After this Special Attack ends, increase the Potency of all personal burst Physical Damage by 100% for 10 seconds."
                ],
                "SPECIAL ATTACK 3": [
                    "After this Special Attack ends, inflict a Degeneration Passive, dealing +71.25 direct damage over 5 seconds per personal Passive effect that has expired on Sauron or on the Opponent. (capped at 30) Reset after Special 3 activation."
                ]
            }
        },
        "3+3": {
            "rank": 3,
            "prestige": "1132",
            "hp": "Offensive: Damage Over Time",
            "attack": "399",
            "crit_rate": "538",
            "crit_dmge": "633",
            "armor": "115",
            "block_prof": "3200",
            "energy_resist": "0",
            "physical_resist": "0",
            "crit_resist": "0",
            "sig_info": [
                "After the start of the fight, if the Opponent attempts to inflict a Bleed, or Incinerate effect while a Degeneration Passive is active, inflict the Opponent with a Passive version of that effect dealing +1197 damage over 2 seconds.",
                "Increase personal Prowess Passive Potency by a flat 1.77 to 7.77%."
            ],
            "url_page": "https://auntm.ai/champions/sauron/tier/3",
            "champid": "sauron+3+3",
            "challenger_rating": 60,
            "abilities": {
                "ALWAYS ACTIVE": [
                    "Immune to all Power Steal, Poison, and Sauron's Regeneration Rate cannot be decreased or increased by outside sources.",
                    "Take -95% less damage from Bleed effects and gain +25% Critical Resistance while Bleeding.",
                    "When Sauron is struck, 30% chance to gain a Regen Passive healing 10% of the damage taken per personal Prowess Passive effect he has.",
                    "Light Attacks have 35% chance to deal 50% of the damage dealt as a burst of Physical Damage. This ability can also trigger through block."
                ],
                "PROWESS (MAX: 10)": [
                    "Each time one of Sauron\u2019s Abilities fails to trigger due to chance gain a 10% Prowess Passive. Gain an additional 2 Prowess Passive if Sauron's Ability fails due to Ability Accuracy modification.",
                    "At 7 Prowess Passives, Dash Attacks, Heavy and Special Attacks grant an Unblockable Passive for 4 seconds. This Unblockable Passive is paused during Special Attacks and has a 10 second cooldown unless Sauron's Ability Accuracy is being modified or Sauron is affected by a Degeneration.",
                    "At 10 Prowess Passives, Dashing Attacks, inflict a Bleed Passive, dealing +299.25 damage over 4 seconds. This ability can also trigger through block.",
                    "Landing the first hit of a Heavy Attack will consume 3 Prowess Passives and gain a Fury Passive, granting +199.5 Attack Rating for 4 seconds"
                ],
                "ALL SPECIAL ATTACKS": [
                    "All Prowess Passives are removed at the end of Special Attacks.",
                    "On activation, pause the Degeneration Passive from Extinction Mode for 8 seconds."
                ],
                "EXTINCTION MODE": [
                    "While at 10 Prowess Passives, when you hit the Opponent, inflict a Degeneration Passive, dealing +159.6 direct damage over 5 seconds.",
                    "Increase Physical Burst Potency by 50% and all personal Abilities have 100% Ability Accuracy.",
                    "If the Degeneration Passive from Extinction Mode expires, remove all Prowess Passives."
                ],
                "SPECIAL ATTACK 1": [
                    "After this Special Attack ends, for each physical burst hit dealt to the Opponent, heal for 25% the damage dealt for 10 seconds."
                ],
                "SPECIAL ATTACK 2": [
                    "After this Special Attack ends, increase the Potency of all personal burst Physical Damage by 100% for 10 seconds."
                ],
                "SPECIAL ATTACK 3": [
                    "After this Special Attack ends, inflict a Degeneration Passive, dealing +99.75 direct damage over 5 seconds per personal Passive effect that has expired on Sauron or on the Opponent. (capped at 30) Reset after Special 3 activation."
                ]
            }
        },
        "3+4": {
            "rank": 4,
            "prestige": "1556",
            "hp": "Offensive: Damage Over Time",
            "attack": "548",
            "crit_rate": "553",
            "crit_dmge": "650",
            "armor": "140",
            "block_prof": "3289",
            "energy_resist": "0",
            "physical_resist": "0",
            "crit_resist": "0",
            "sig_info": [
                "After the start of the fight, if the Opponent attempts to inflict a Bleed, or Incinerate effect while a Degeneration Passive is active, inflict the Opponent with a Passive version of that effect dealing +1644 damage over 2 seconds.",
                "Increase personal Prowess Passive Potency by a flat 1.77 to 7.77%."
            ],
            "url_page": "https://auntm.ai/champions/sauron/tier/3",
            "champid": "sauron+3+4",
            "challenger_rating": 70,
            "abilities": {
                "ALWAYS ACTIVE": [
                    "Immune to all Power Steal, Poison, and Sauron's Regeneration Rate cannot be decreased or increased by outside sources.",
                    "Take -95% less damage from Bleed effects and gain +25% Critical Resistance while Bleeding.",
                    "When Sauron is struck, 30% chance to gain a Regen Passive healing 10% of the damage taken per personal Prowess Passive effect he has.",
                    "Light Attacks have 35% chance to deal 50% of the damage dealt as a burst of Physical Damage. This ability can also trigger through block."
                ],
                "PROWESS (MAX: 10)": [
                    "Each time one of Sauron\u2019s Abilities fails to trigger due to chance gain a 10% Prowess Passive. Gain an additional 2 Prowess Passive if Sauron's Ability fails due to Ability Accuracy modification.",
                    "At 7 Prowess Passives, Dash Attacks, Heavy and Special Attacks grant an Unblockable Passive for 4 seconds. This Unblockable Passive is paused during Special Attacks and has a 10 second cooldown unless Sauron's Ability Accuracy is being modified or Sauron is affected by a Degeneration.",
                    "At 10 Prowess Passives, Dashing Attacks, inflict a Bleed Passive, dealing +411 damage over 4 seconds. This ability can also trigger through block.",
                    "Landing the first hit of a Heavy Attack will consume 3 Prowess Passives and gain a Fury Passive, granting +274 Attack Rating for 4 seconds"
                ],
                "ALL SPECIAL ATTACKS": [
                    "All Prowess Passives are removed at the end of Special Attacks.",
                    "On activation, pause the Degeneration Passive from Extinction Mode for 8 seconds."
                ],
                "EXTINCTION MODE": [
                    "While at 10 Prowess Passives, when you hit the Opponent, inflict a Degeneration Passive, dealing +219.2 direct damage over 5 seconds.",
                    "Increase Physical Burst Potency by 50% and all personal Abilities have 100% Ability Accuracy.",
                    "If the Degeneration Passive from Extinction Mode expires, remove all Prowess Passives."
                ],
                "SPECIAL ATTACK 1": [
                    "After this Special Attack ends, for each physical burst hit dealt to the Opponent, heal for 25% the damage dealt for 10 seconds."
                ],
                "SPECIAL ATTACK 2": [
                    "After this Special Attack ends, increase the Potency of all personal burst Physical Damage by 100% for 10 seconds."
                ],
                "SPECIAL ATTACK 3": [
                    "After this Special Attack ends, inflict a Degeneration Passive, dealing +137 direct damage over 5 seconds per personal Passive effect that has expired on Sauron or on the Opponent. (capped at 30) Reset after Special 3 activation."
                ]
            }
        },
        "4+1": {
            "rank": 1,
            "prestige": "1131",
            "hp": "Offensive: Damage Over Time",
            "attack": "399",
            "crit_rate": "538",
            "crit_dmge": "633",
            "armor": "157",
            "block_prof": "3200",
            "energy_resist": "0",
            "physical_resist": "0",
            "crit_resist": "0",
            "sig_info": [
                "After the start of the fight, if the Opponent attempts to inflict a Bleed, or Incinerate effect while a Degeneration Passive is active, inflict the Opponent with a Passive version of that effect dealing +1197 damage over 2 seconds.",
                "Increase personal Prowess Passive Potency by a flat 1.77 to 7.77%."
            ],
            "url_page": "https://auntm.ai/champions/sauron/tier/4",
            "champid": "sauron+4+1",
            "challenger_rating": 60,
            "abilities": {
                "ALWAYS ACTIVE": [
                    "Immune to all Power Steal, Poison, and Sauron's Regeneration Rate cannot be decreased or increased by outside sources.",
                    "Take -95% less damage from Bleed effects and gain +25% Critical Resistance while Bleeding.",
                    "When Sauron is struck, 30% chance to gain a Regen Passive healing 10% of the damage taken per personal Prowess Passive effect he has.",
                    "Light Attacks have 35% chance to deal 50% of the damage dealt as a burst of Physical Damage. This ability can also trigger through block."
                ],
                "PROWESS (MAX: 10)": [
                    "Each time one of Sauron\u2019s Abilities fails to trigger due to chance gain a 10% Prowess Passive. Gain an additional 2 Prowess Passive if Sauron's Ability fails due to Ability Accuracy modification.",
                    "At 7 Prowess Passives, Dash Attacks, Heavy and Special Attacks grant an Unblockable Passive for 4 seconds. This Unblockable Passive is paused during Special Attacks and has a 10 second cooldown unless Sauron's Ability Accuracy is being modified or Sauron is affected by a Degeneration.",
                    "At 10 Prowess Passives, Dashing Attacks, inflict a Bleed Passive, dealing +299.25 damage over 4 seconds. This ability can also trigger through block.",
                    "Landing the first hit of a Heavy Attack will consume 3 Prowess Passives and gain a Fury Passive, granting +199.5 Attack Rating for 4 seconds"
                ],
                "ALL SPECIAL ATTACKS": [
                    "All Prowess Passives are removed at the end of Special Attacks.",
                    "On activation, pause the Degeneration Passive from Extinction Mode for 8 seconds."
                ],
                "EXTINCTION MODE": [
                    "While at 10 Prowess Passives, when you hit the Opponent, inflict a Degeneration Passive, dealing +159.6 direct damage over 5 seconds.",
                    "Increase Physical Burst Potency by 50% and all personal Abilities have 100% Ability Accuracy.",
                    "If the Degeneration Passive from Extinction Mode expires, remove all Prowess Passives."
                ],
                "SPECIAL ATTACK 1": [
                    "After this Special Attack ends, for each physical burst hit dealt to the Opponent, heal for 25% the damage dealt for 10 seconds."
                ],
                "SPECIAL ATTACK 2": [
                    "After this Special Attack ends, increase the Potency of all personal burst Physical Damage by 100% for 10 seconds."
                ],
                "SPECIAL ATTACK 3": [
                    "After this Special Attack ends, inflict a Degeneration Passive, dealing +99.75 direct damage over 5 seconds per personal Passive effect that has expired on Sauron or on the Opponent. (capped at 30) Reset after Special 3 activation."
                ]
            }
        },
        "4+2": {
            "rank": 2,
            "prestige": "1590",
            "hp": "Offensive: Damage Over Time",
            "attack": "559",
            "crit_rate": "553",
            "crit_dmge": "650",
            "armor": "183",
            "block_prof": "3289",
            "energy_resist": "0",
            "physical_resist": "0",
            "crit_resist": "0",
            "sig_info": [
                "After the start of the fight, if the Opponent attempts to inflict a Bleed, or Incinerate effect while a Degeneration Passive is active, inflict the Opponent with a Passive version of that effect dealing +1677 damage over 2 seconds.",
                "Increase personal Prowess Passive Potency by a flat 1.77 to 7.77%."
            ],
            "url_page": "https://auntm.ai/champions/sauron/tier/4",
            "champid": "sauron+4+2",
            "challenger_rating": 70,
            "abilities": {
                "ALWAYS ACTIVE": [
                    "Immune to all Power Steal, Poison, and Sauron's Regeneration Rate cannot be decreased or increased by outside sources.",
                    "Take -95% less damage from Bleed effects and gain +25% Critical Resistance while Bleeding.",
                    "When Sauron is struck, 30% chance to gain a Regen Passive healing 10% of the damage taken per personal Prowess Passive effect he has.",
                    "Light Attacks have 35% chance to deal 50% of the damage dealt as a burst of Physical Damage. This ability can also trigger through block."
                ],
                "PROWESS (MAX: 10)": [
                    "Each time one of Sauron\u2019s Abilities fails to trigger due to chance gain a 10% Prowess Passive. Gain an additional 2 Prowess Passive if Sauron's Ability fails due to Ability Accuracy modification.",
                    "At 7 Prowess Passives, Dash Attacks, Heavy and Special Attacks grant an Unblockable Passive for 4 seconds. This Unblockable Passive is paused during Special Attacks and has a 10 second cooldown unless Sauron's Ability Accuracy is being modified or Sauron is affected by a Degeneration.",
                    "At 10 Prowess Passives, Dashing Attacks, inflict a Bleed Passive, dealing +419.25 damage over 4 seconds. This ability can also trigger through block.",
                    "Landing the first hit of a Heavy Attack will consume 3 Prowess Passives and gain a Fury Passive, granting +279.5 Attack Rating for 4 seconds"
                ],
                "ALL SPECIAL ATTACKS": [
                    "All Prowess Passives are removed at the end of Special Attacks.",
                    "On activation, pause the Degeneration Passive from Extinction Mode for 8 seconds."
                ],
                "EXTINCTION MODE": [
                    "While at 10 Prowess Passives, when you hit the Opponent, inflict a Degeneration Passive, dealing +223.6 direct damage over 5 seconds.",
                    "Increase Physical Burst Potency by 50% and all personal Abilities have 100% Ability Accuracy.",
                    "If the Degeneration Passive from Extinction Mode expires, remove all Prowess Passives."
                ],
                "SPECIAL ATTACK 1": [
                    "After this Special Attack ends, for each physical burst hit dealt to the Opponent, heal for 25% the damage dealt for 10 seconds."
                ],
                "SPECIAL ATTACK 2": [
                    "After this Special Attack ends, increase the Potency of all personal burst Physical Damage by 100% for 10 seconds."
                ],
                "SPECIAL ATTACK 3": [
                    "After this Special Attack ends, inflict a Degeneration Passive, dealing +139.75 direct damage over 5 seconds per personal Passive effect that has expired on Sauron or on the Opponent. (capped at 30) Reset after Special 3 activation."
                ]
            }
        },
        "4+3": {
            "rank": 3,
            "prestige": "2226",
            "hp": "Offensive: Damage Over Time",
            "attack": "783",
            "crit_rate": "568",
            "crit_dmge": "668",
            "armor": "212",
            "block_prof": "3378",
            "energy_resist": "0",
            "physical_resist": "0",
            "crit_resist": "0",
            "sig_info": [
                "After the start of the fight, if the Opponent attempts to inflict a Bleed, or Incinerate effect while a Degeneration Passive is active, inflict the Opponent with a Passive version of that effect dealing +2349 damage over 2 seconds.",
                "Increase personal Prowess Passive Potency by a flat 1.77 to 7.77%."
            ],
            "url_page": "https://auntm.ai/champions/sauron/tier/4",
            "champid": "sauron+4+3",
            "challenger_rating": 80,
            "abilities": {
                "ALWAYS ACTIVE": [
                    "Immune to all Power Steal, Poison, and Sauron's Regeneration Rate cannot be decreased or increased by outside sources.",
                    "Take -95% less damage from Bleed effects and gain +25% Critical Resistance while Bleeding.",
                    "When Sauron is struck, 30% chance to gain a Regen Passive healing 10% of the damage taken per personal Prowess Passive effect he has.",
                    "Light Attacks have 35% chance to deal 50% of the damage dealt as a burst of Physical Damage. This ability can also trigger through block."
                ],
                "PROWESS (MAX: 10)": [
                    "Each time one of Sauron\u2019s Abilities fails to trigger due to chance gain a 10% Prowess Passive. Gain an additional 2 Prowess Passive if Sauron's Ability fails due to Ability Accuracy modification.",
                    "At 7 Prowess Passives, Dash Attacks, Heavy and Special Attacks grant an Unblockable Passive for 4 seconds. This Unblockable Passive is paused during Special Attacks and has a 10 second cooldown unless Sauron's Ability Accuracy is being modified or Sauron is affected by a Degeneration.",
                    "At 10 Prowess Passives, Dashing Attacks, inflict a Bleed Passive, dealing +587.25 damage over 4 seconds. This ability can also trigger through block.",
                    "Landing the first hit of a Heavy Attack will consume 3 Prowess Passives and gain a Fury Passive, granting +391.5 Attack Rating for 4 seconds"
                ],
                "ALL SPECIAL ATTACKS": [
                    "All Prowess Passives are removed at the end of Special Attacks.",
                    "On activation, pause the Degeneration Passive from Extinction Mode for 8 seconds."
                ],
                "EXTINCTION MODE": [
                    "While at 10 Prowess Passives, when you hit the Opponent, inflict a Degeneration Passive, dealing +313.2 direct damage over 5 seconds.",
                    "Increase Physical Burst Potency by 50% and all personal Abilities have 100% Ability Accuracy.",
                    "If the Degeneration Passive from Extinction Mode expires, remove all Prowess Passives."
                ],
                "SPECIAL ATTACK 1": [
                    "After this Special Attack ends, for each physical burst hit dealt to the Opponent, heal for 25% the damage dealt for 10 seconds."
                ],
                "SPECIAL ATTACK 2": [
                    "After this Special Attack ends, increase the Potency of all personal burst Physical Damage by 100% for 10 seconds."
                ],
                "SPECIAL ATTACK 3": [
                    "After this Special Attack ends, inflict a Degeneration Passive, dealing +195.75 direct damage over 5 seconds per personal Passive effect that has expired on Sauron or on the Opponent. (capped at 30) Reset after Special 3 activation."
                ]
            }
        },
        "4+4": {
            "rank": 4,
            "prestige": "2931",
            "hp": "Offensive: Damage Over Time",
            "attack": "1029",
            "crit_rate": "583",
            "crit_dmge": "686",
            "armor": "242",
            "block_prof": "3467",
            "energy_resist": "0",
            "physical_resist": "0",
            "crit_resist": "0",
            "sig_info": [
                "After the start of the fight, if the Opponent attempts to inflict a Bleed, or Incinerate effect while a Degeneration Passive is active, inflict the Opponent with a Passive version of that effect dealing +3087 damage over 2 seconds.",
                "Increase personal Prowess Passive Potency by a flat 1.77 to 7.77%."
            ],
            "url_page": "https://auntm.ai/champions/sauron/tier/4",
            "champid": "sauron+4+4",
            "challenger_rating": 90,
            "abilities": {
                "ALWAYS ACTIVE": [
                    "Immune to all Power Steal, Poison, and Sauron's Regeneration Rate cannot be decreased or increased by outside sources.",
                    "Take -95% less damage from Bleed effects and gain +25% Critical Resistance while Bleeding.",
                    "When Sauron is struck, 30% chance to gain a Regen Passive healing 10% of the damage taken per personal Prowess Passive effect he has.",
                    "Light Attacks have 35% chance to deal 50% of the damage dealt as a burst of Physical Damage. This ability can also trigger through block."
                ],
                "PROWESS (MAX: 10)": [
                    "Each time one of Sauron\u2019s Abilities fails to trigger due to chance gain a 10% Prowess Passive. Gain an additional 2 Prowess Passive if Sauron's Ability fails due to Ability Accuracy modification.",
                    "At 7 Prowess Passives, Dash Attacks, Heavy and Special Attacks grant an Unblockable Passive for 4 seconds. This Unblockable Passive is paused during Special Attacks and has a 10 second cooldown unless Sauron's Ability Accuracy is being modified or Sauron is affected by a Degeneration.",
                    "At 10 Prowess Passives, Dashing Attacks, inflict a Bleed Passive, dealing +771.75 damage over 4 seconds. This ability can also trigger through block.",
                    "Landing the first hit of a Heavy Attack will consume 3 Prowess Passives and gain a Fury Passive, granting +514.5 Attack Rating for 4 seconds"
                ],
                "ALL SPECIAL ATTACKS": [
                    "All Prowess Passives are removed at the end of Special Attacks.",
                    "On activation, pause the Degeneration Passive from Extinction Mode for 8 seconds."
                ],
                "EXTINCTION MODE": [
                    "While at 10 Prowess Passives, when you hit the Opponent, inflict a Degeneration Passive, dealing +411.6 direct damage over 5 seconds.",
                    "Increase Physical Burst Potency by 50% and all personal Abilities have 100% Ability Accuracy.",
                    "If the Degeneration Passive from Extinction Mode expires, remove all Prowess Passives."
                ],
                "SPECIAL ATTACK 1": [
                    "After this Special Attack ends, for each physical burst hit dealt to the Opponent, heal for 25% the damage dealt for 10 seconds."
                ],
                "SPECIAL ATTACK 2": [
                    "After this Special Attack ends, increase the Potency of all personal burst Physical Damage by 100% for 10 seconds."
                ],
                "SPECIAL ATTACK 3": [
                    "After this Special Attack ends, inflict a Degeneration Passive, dealing +257.25 direct damage over 5 seconds per personal Passive effect that has expired on Sauron or on the Opponent. (capped at 30) Reset after Special 3 activation."
                ]
            }
        },
        "4+5": {
            "rank": 5,
            "prestige": "3908",
            "hp": "Offensive: Damage Over Time",
            "attack": "1373",
            "crit_rate": "598",
            "crit_dmge": "703",
            "armor": "273",
            "block_prof": "3556",
            "energy_resist": "0",
            "physical_resist": "0",
            "crit_resist": "0",
            "sig_info": [
                "After the start of the fight, if the Opponent attempts to inflict a Bleed, or Incinerate effect while a Degeneration Passive is active, inflict the Opponent with a Passive version of that effect dealing +4119 damage over 2 seconds.",
                "Increase personal Prowess Passive Potency by a flat 1.77 to 7.77%."
            ],
            "url_page": "https://auntm.ai/champions/sauron/tier/4",
            "champid": "sauron+4+5",
            "challenger_rating": 100,
            "abilities": {
                "ALWAYS ACTIVE": [
                    "Immune to all Power Steal, Poison, and Sauron's Regeneration Rate cannot be decreased or increased by outside sources.",
                    "Take -95% less damage from Bleed effects and gain +25% Critical Resistance while Bleeding.",
                    "When Sauron is struck, 30% chance to gain a Regen Passive healing 10% of the damage taken per personal Prowess Passive effect he has.",
                    "Light Attacks have 35% chance to deal 50% of the damage dealt as a burst of Physical Damage. This ability can also trigger through block."
                ],
                "PROWESS (MAX: 10)": [
                    "Each time one of Sauron\u2019s Abilities fails to trigger due to chance gain a 10% Prowess Passive. Gain an additional 2 Prowess Passive if Sauron's Ability fails due to Ability Accuracy modification.",
                    "At 7 Prowess Passives, Dash Attacks, Heavy and Special Attacks grant an Unblockable Passive for 4 seconds. This Unblockable Passive is paused during Special Attacks and has a 10 second cooldown unless Sauron's Ability Accuracy is being modified or Sauron is affected by a Degeneration.",
                    "At 10 Prowess Passives, Dashing Attacks, inflict a Bleed Passive, dealing +1029.75 damage over 4 seconds. This ability can also trigger through block.",
                    "Landing the first hit of a Heavy Attack will consume 3 Prowess Passives and gain a Fury Passive, granting +686.5 Attack Rating for 4 seconds"
                ],
                "ALL SPECIAL ATTACKS": [
                    "All Prowess Passives are removed at the end of Special Attacks.",
                    "On activation, pause the Degeneration Passive from Extinction Mode for 8 seconds."
                ],
                "EXTINCTION MODE": [
                    "While at 10 Prowess Passives, when you hit the Opponent, inflict a Degeneration Passive, dealing +549.2 direct damage over 5 seconds.",
                    "Increase Physical Burst Potency by 50% and all personal Abilities have 100% Ability Accuracy.",
                    "If the Degeneration Passive from Extinction Mode expires, remove all Prowess Passives."
                ],
                "SPECIAL ATTACK 1": [
                    "After this Special Attack ends, for each physical burst hit dealt to the Opponent, heal for 25% the damage dealt for 10 seconds."
                ],
                "SPECIAL ATTACK 2": [
                    "After this Special Attack ends, increase the Potency of all personal burst Physical Damage by 100% for 10 seconds."
                ],
                "SPECIAL ATTACK 3": [
                    "After this Special Attack ends, inflict a Degeneration Passive, dealing +343.25 direct damage over 5 seconds per personal Passive effect that has expired on Sauron or on the Opponent. (capped at 30) Reset after Special 3 activation."
                ]
            }
        },
        "5+1": {
            "rank": 1,
            "prestige": "2341",
            "hp": "Offensive: Damage Over Time",
            "attack": "820",
            "crit_rate": "568",
            "crit_dmge": "668",
            "armor": "362",
            "block_prof": "3378",
            "energy_resist": "0",
            "physical_resist": "0",
            "crit_resist": "0",
            "sig_info": [
                "After the start of the fight, if the Opponent attempts to inflict a Bleed, or Incinerate effect while a Degeneration Passive is active, inflict the Opponent with a Passive version of that effect dealing +2460 damage over 2 seconds.",
                "Increase personal Prowess Passive Potency by a flat 2 to 10%."
            ],
            "url_page": "https://auntm.ai/champions/sauron/tier/5",
            "champid": "sauron+5+1",
            "challenger_rating": 80,
            "abilities": {
                "ALWAYS ACTIVE": [
                    "Immune to all Power Steal, Poison, and Sauron's Regeneration Rate cannot be decreased or increased by outside sources.",
                    "Take -95% less damage from Bleed effects and gain +25% Critical Resistance while Bleeding.",
                    "When Sauron is struck, 30% chance to gain a Regen Passive healing 10% of the damage taken per personal Prowess Passive effect he has.",
                    "Light Attacks have 35% chance to deal 50% of the damage dealt as a burst of Physical Damage. This ability can also trigger through block."
                ],
                "PROWESS (MAX: 10)": [
                    "Each time one of Sauron\u2019s Abilities fails to trigger due to chance gain a 10% Prowess Passive. Gain an additional 2 Prowess Passive if Sauron's Ability fails due to Ability Accuracy modification.",
                    "At 7 Prowess Passives, Dash Attacks, Heavy and Special Attacks grant an Unblockable Passive for 4 seconds. This Unblockable Passive is paused during Special Attacks and has a 10 second cooldown unless Sauron's Ability Accuracy is being modified or Sauron is affected by a Degeneration.",
                    "At 10 Prowess Passives, Dashing Attacks, inflict a Bleed Passive, dealing +615 damage over 4 seconds. This ability can also trigger through block.",
                    "Landing the first hit of a Heavy Attack will consume 3 Prowess Passives and gain a Fury Passive, granting +410 Attack Rating for 4 seconds"
                ],
                "ALL SPECIAL ATTACKS": [
                    "All Prowess Passives are removed at the end of Special Attacks.",
                    "On activation, pause the Degeneration Passive from Extinction Mode for 8 seconds."
                ],
                "EXTINCTION MODE": [
                    "While at 10 Prowess Passives, when you hit the Opponent, inflict a Degeneration Passive, dealing +328 direct damage over 5 seconds.",
                    "Increase Physical Burst Potency by 50% and all personal Abilities have 100% Ability Accuracy.",
                    "If the Degeneration Passive from Extinction Mode expires, remove all Prowess Passives."
                ],
                "SPECIAL ATTACK 1": [
                    "After this Special Attack ends, for each physical burst hit dealt to the Opponent, heal for 25% the damage dealt for 10 seconds."
                ],
                "SPECIAL ATTACK 2": [
                    "After this Special Attack ends, increase the Potency of all personal burst Physical Damage by 100% for 10 seconds."
                ],
                "SPECIAL ATTACK 3": [
                    "After this Special Attack ends, inflict a Degeneration Passive, dealing +205 direct damage over 5 seconds per personal Passive effect that has expired on Sauron or on the Opponent. (capped at 30) Reset after Special 3 activation."
                ]
            }
        },
        "5+2": {
            "rank": 2,
            "prestige": "3089",
            "hp": "Offensive: Damage Over Time",
            "attack": "1082",
            "crit_rate": "583",
            "crit_dmge": "686",
            "armor": "400",
            "block_prof": "3467",
            "energy_resist": "0",
            "physical_resist": "0",
            "crit_resist": "0",
            "sig_info": [
                "After the start of the fight, if the Opponent attempts to inflict a Bleed, or Incinerate effect while a Degeneration Passive is active, inflict the Opponent with a Passive version of that effect dealing +3246 damage over 2 seconds.",
                "Increase personal Prowess Passive Potency by a flat 2 to 10%."
            ],
            "url_page": "https://auntm.ai/champions/sauron/tier/5",
            "champid": "sauron+5+2",
            "challenger_rating": 90,
            "abilities": {
                "ALWAYS ACTIVE": [
                    "Immune to all Power Steal, Poison, and Sauron's Regeneration Rate cannot be decreased or increased by outside sources.",
                    "Take -95% less damage from Bleed effects and gain +25% Critical Resistance while Bleeding.",
                    "When Sauron is struck, 30% chance to gain a Regen Passive healing 10% of the damage taken per personal Prowess Passive effect he has.",
                    "Light Attacks have 35% chance to deal 50% of the damage dealt as a burst of Physical Damage. This ability can also trigger through block."
                ],
                "PROWESS (MAX: 10)": [
                    "Each time one of Sauron\u2019s Abilities fails to trigger due to chance gain a 10% Prowess Passive. Gain an additional 2 Prowess Passive if Sauron's Ability fails due to Ability Accuracy modification.",
                    "At 7 Prowess Passives, Dash Attacks, Heavy and Special Attacks grant an Unblockable Passive for 4 seconds. This Unblockable Passive is paused during Special Attacks and has a 10 second cooldown unless Sauron's Ability Accuracy is being modified or Sauron is affected by a Degeneration.",
                    "At 10 Prowess Passives, Dashing Attacks, inflict a Bleed Passive, dealing +811.5 damage over 4 seconds. This ability can also trigger through block.",
                    "Landing the first hit of a Heavy Attack will consume 3 Prowess Passives and gain a Fury Passive, granting +541 Attack Rating for 4 seconds"
                ],
                "ALL SPECIAL ATTACKS": [
                    "All Prowess Passives are removed at the end of Special Attacks.",
                    "On activation, pause the Degeneration Passive from Extinction Mode for 8 seconds."
                ],
                "EXTINCTION MODE": [
                    "While at 10 Prowess Passives, when you hit the Opponent, inflict a Degeneration Passive, dealing +432.8 direct damage over 5 seconds.",
                    "Increase Physical Burst Potency by 50% and all personal Abilities have 100% Ability Accuracy.",
                    "If the Degeneration Passive from Extinction Mode expires, remove all Prowess Passives."
                ],
                "SPECIAL ATTACK 1": [
                    "After this Special Attack ends, for each physical burst hit dealt to the Opponent, heal for 25% the damage dealt for 10 seconds."
                ],
                "SPECIAL ATTACK 2": [
                    "After this Special Attack ends, increase the Potency of all personal burst Physical Damage by 100% for 10 seconds."
                ],
                "SPECIAL ATTACK 3": [
                    "After this Special Attack ends, inflict a Degeneration Passive, dealing +270.5 direct damage over 5 seconds per personal Passive effect that has expired on Sauron or on the Opponent. (capped at 30) Reset after Special 3 activation."
                ]
            }
        },
        "5+3": {
            "rank": 3,
            "prestige": "4325",
            "hp": "Offensive: Damage Over Time",
            "attack": "1513",
            "crit_rate": "598",
            "crit_dmge": "703",
            "armor": "440",
            "block_prof": "3556",
            "energy_resist": "0",
            "physical_resist": "0",
            "crit_resist": "0",
            "sig_info": [
                "After the start of the fight, if the Opponent attempts to inflict a Bleed, or Incinerate effect while a Degeneration Passive is active, inflict the Opponent with a Passive version of that effect dealing +4539 damage over 2 seconds.",
                "Increase personal Prowess Passive Potency by a flat 2 to 10%."
            ],
            "url_page": "https://auntm.ai/champions/sauron/tier/5",
            "champid": "sauron+5+3",
            "challenger_rating": 100,
            "abilities": {
                "ALWAYS ACTIVE": [
                    "Immune to all Power Steal, Poison, and Sauron's Regeneration Rate cannot be decreased or increased by outside sources.",
                    "Take -95% less damage from Bleed effects and gain +25% Critical Resistance while Bleeding.",
                    "When Sauron is struck, 30% chance to gain a Regen Passive healing 10% of the damage taken per personal Prowess Passive effect he has.",
                    "Light Attacks have 35% chance to deal 50% of the damage dealt as a burst of Physical Damage. This ability can also trigger through block."
                ],
                "PROWESS (MAX: 10)": [
                    "Each time one of Sauron\u2019s Abilities fails to trigger due to chance gain a 10% Prowess Passive. Gain an additional 2 Prowess Passive if Sauron's Ability fails due to Ability Accuracy modification.",
                    "At 7 Prowess Passives, Dash Attacks, Heavy and Special Attacks grant an Unblockable Passive for 4 seconds. This Unblockable Passive is paused during Special Attacks and has a 10 second cooldown unless Sauron's Ability Accuracy is being modified or Sauron is affected by a Degeneration.",
                    "At 10 Prowess Passives, Dashing Attacks, inflict a Bleed Passive, dealing +1134.75 damage over 4 seconds. This ability can also trigger through block.",
                    "Landing the first hit of a Heavy Attack will consume 3 Prowess Passives and gain a Fury Passive, granting +756.5 Attack Rating for 4 seconds"
                ],
                "ALL SPECIAL ATTACKS": [
                    "All Prowess Passives are removed at the end of Special Attacks.",
                    "On activation, pause the Degeneration Passive from Extinction Mode for 8 seconds."
                ],
                "EXTINCTION MODE": [
                    "While at 10 Prowess Passives, when you hit the Opponent, inflict a Degeneration Passive, dealing +605.2 direct damage over 5 seconds.",
                    "Increase Physical Burst Potency by 50% and all personal Abilities have 100% Ability Accuracy.",
                    "If the Degeneration Passive from Extinction Mode expires, remove all Prowess Passives."
                ],
                "SPECIAL ATTACK 1": [
                    "After this Special Attack ends, for each physical burst hit dealt to the Opponent, heal for 25% the damage dealt for 10 seconds."
                ],
                "SPECIAL ATTACK 2": [
                    "After this Special Attack ends, increase the Potency of all personal burst Physical Damage by 100% for 10 seconds."
                ],
                "SPECIAL ATTACK 3": [
                    "After this Special Attack ends, inflict a Degeneration Passive, dealing +378.25 direct damage over 5 seconds per personal Passive effect that has expired on Sauron or on the Opponent. (capped at 30) Reset after Special 3 activation."
                ]
            }
        },
        "5+4": {
            "rank": 4,
            "prestige": "5827",
            "hp": "Offensive: Damage Over Time",
            "attack": "2039",
            "crit_rate": "613",
            "crit_dmge": "721",
            "armor": "481",
            "block_prof": "3645",
            "energy_resist": "0",
            "physical_resist": "0",
            "crit_resist": "0",
            "sig_info": [
                "After the start of the fight, if the Opponent attempts to inflict a Bleed, or Incinerate effect while a Degeneration Passive is active, inflict the Opponent with a Passive version of that effect dealing +6117 damage over 2 seconds.",
                "Increase personal Prowess Passive Potency by a flat 2 to 10%."
            ],
            "url_page": "https://auntm.ai/champions/sauron/tier/5",
            "champid": "sauron+5+4",
            "challenger_rating": 110,
            "abilities": {
                "ALWAYS ACTIVE": [
                    "Immune to all Power Steal, Poison, and Sauron's Regeneration Rate cannot be decreased or increased by outside sources.",
                    "Take -95% less damage from Bleed effects and gain +25% Critical Resistance while Bleeding.",
                    "When Sauron is struck, 30% chance to gain a Regen Passive healing 10% of the damage taken per personal Prowess Passive effect he has.",
                    "Light Attacks have 35% chance to deal 50% of the damage dealt as a burst of Physical Damage. This ability can also trigger through block."
                ],
                "PROWESS (MAX: 10)": [
                    "Each time one of Sauron\u2019s Abilities fails to trigger due to chance gain a 10% Prowess Passive. Gain an additional 2 Prowess Passive if Sauron's Ability fails due to Ability Accuracy modification.",
                    "At 7 Prowess Passives, Dash Attacks, Heavy and Special Attacks grant an Unblockable Passive for 4 seconds. This Unblockable Passive is paused during Special Attacks and has a 10 second cooldown unless Sauron's Ability Accuracy is being modified or Sauron is affected by a Degeneration.",
                    "At 10 Prowess Passives, Dashing Attacks, inflict a Bleed Passive, dealing +1529.25 damage over 4 seconds. This ability can also trigger through block.",
                    "Landing the first hit of a Heavy Attack will consume 3 Prowess Passives and gain a Fury Passive, granting +1019.5 Attack Rating for 4 seconds"
                ],
                "ALL SPECIAL ATTACKS": [
                    "All Prowess Passives are removed at the end of Special Attacks.",
                    "On activation, pause the Degeneration Passive from Extinction Mode for 8 seconds."
                ],
                "EXTINCTION MODE": [
                    "While at 10 Prowess Passives, when you hit the Opponent, inflict a Degeneration Passive, dealing +815.6 direct damage over 5 seconds.",
                    "Increase Physical Burst Potency by 50% and all personal Abilities have 100% Ability Accuracy.",
                    "If the Degeneration Passive from Extinction Mode expires, remove all Prowess Passives."
                ],
                "SPECIAL ATTACK 1": [
                    "After this Special Attack ends, for each physical burst hit dealt to the Opponent, heal for 25% the damage dealt for 10 seconds."
                ],
                "SPECIAL ATTACK 2": [
                    "After this Special Attack ends, increase the Potency of all personal burst Physical Damage by 100% for 10 seconds."
                ],
                "SPECIAL ATTACK 3": [
                    "After this Special Attack ends, inflict a Degeneration Passive, dealing +509.75 direct damage over 5 seconds per personal Passive effect that has expired on Sauron or on the Opponent. (capped at 30) Reset after Special 3 activation."
                ]
            }
        },
        "5+5": {
            "rank": 5,
            "prestige": "7881",
            "hp": "Offensive: Damage Over Time",
            "attack": "2753",
            "crit_rate": "628",
            "crit_dmge": "738",
            "armor": "525",
            "block_prof": "3734",
            "energy_resist": "0",
            "physical_resist": "0",
            "crit_resist": "0",
            "sig_info": [
                "After the start of the fight, if the Opponent attempts to inflict a Bleed, or Incinerate effect while a Degeneration Passive is active, inflict the Opponent with a Passive version of that effect dealing +8259 damage over 2 seconds.",
                "Increase personal Prowess Passive Potency by a flat 2 to 10%."
            ],
            "url_page": "https://auntm.ai/champions/sauron/tier/5",
            "champid": "sauron+5+5",
            "challenger_rating": 120,
            "abilities": {
                "ALWAYS ACTIVE": [
                    "Immune to all Power Steal, Poison, and Sauron's Regeneration Rate cannot be decreased or increased by outside sources.",
                    "Take -95% less damage from Bleed effects and gain +25% Critical Resistance while Bleeding.",
                    "When Sauron is struck, 30% chance to gain a Regen Passive healing 10% of the damage taken per personal Prowess Passive effect he has.",
                    "Light Attacks have 35% chance to deal 50% of the damage dealt as a burst of Physical Damage. This ability can also trigger through block."
                ],
                "PROWESS (MAX: 10)": [
                    "Each time one of Sauron\u2019s Abilities fails to trigger due to chance gain a 10% Prowess Passive. Gain an additional 2 Prowess Passive if Sauron's Ability fails due to Ability Accuracy modification.",
                    "At 7 Prowess Passives, Dash Attacks, Heavy and Special Attacks grant an Unblockable Passive for 4 seconds. This Unblockable Passive is paused during Special Attacks and has a 10 second cooldown unless Sauron's Ability Accuracy is being modified or Sauron is affected by a Degeneration.",
                    "At 10 Prowess Passives, Dashing Attacks, inflict a Bleed Passive, dealing +2064.75 damage over 4 seconds. This ability can also trigger through block.",
                    "Landing the first hit of a Heavy Attack will consume 3 Prowess Passives and gain a Fury Passive, granting +1376.5 Attack Rating for 4 seconds"
                ],
                "ALL SPECIAL ATTACKS": [
                    "All Prowess Passives are removed at the end of Special Attacks.",
                    "On activation, pause the Degeneration Passive from Extinction Mode for 8 seconds."
                ],
                "EXTINCTION MODE": [
                    "While at 10 Prowess Passives, when you hit the Opponent, inflict a Degeneration Passive, dealing +1101.2 direct damage over 5 seconds.",
                    "Increase Physical Burst Potency by 50% and all personal Abilities have 100% Ability Accuracy.",
                    "If the Degeneration Passive from Extinction Mode expires, remove all Prowess Passives."
                ],
                "SPECIAL ATTACK 1": [
                    "After this Special Attack ends, for each physical burst hit dealt to the Opponent, heal for 25% the damage dealt for 10 seconds."
                ],
                "SPECIAL ATTACK 2": [
                    "After this Special Attack ends, increase the Potency of all personal burst Physical Damage by 100% for 10 seconds."
                ],
                "SPECIAL ATTACK 3": [
                    "After this Special Attack ends, inflict a Degeneration Passive, dealing +688.25 direct damage over 5 seconds per personal Passive effect that has expired on Sauron or on the Opponent. (capped at 30) Reset after Special 3 activation."
                ]
            }
        },
        "6+1": {
            "rank": 1,
            "prestige": "6172",
            "hp": "Offensive: Damage Over Time",
            "attack": "2164",
            "crit_rate": "613",
            "crit_dmge": "721",
            "armor": "391",
            "block_prof": "3645",
            "energy_resist": "0",
            "physical_resist": "0",
            "crit_resist": "0",
            "sig_info": [
                "After the start of the fight, if the Opponent attempts to inflict a Bleed, or Incinerate effect while a Degeneration Passive is active, inflict the Opponent with a Passive version of that effect dealing +6492 damage over 2 seconds.",
                "Increase personal Prowess Passive Potency by a flat 2 to 10%."
            ],
            "url_page": "https://auntm.ai/champions/sauron/tier/6",
            "champid": "sauron+6+1",
            "challenger_rating": 110,
            "abilities": {
                "ALWAYS ACTIVE": [
                    "Immune to all Power Steal, Poison, and Sauron's Regeneration Rate cannot be decreased or increased by outside sources.",
                    "Take -95% less damage from Bleed effects and gain +25% Critical Resistance while Bleeding.",
                    "When Sauron is struck, 30% chance to gain a Regen Passive healing 10% of the damage taken per personal Prowess Passive effect he has.",
                    "Light Attacks have 35% chance to deal 50% of the damage dealt as a burst of Physical Damage. This ability can also trigger through block."
                ],
                "PROWESS (MAX: 10)": [
                    "Each time one of Sauron\u2019s Abilities fails to trigger due to chance gain a 10% Prowess Passive. Gain an additional 2 Prowess Passive if Sauron's Ability fails due to Ability Accuracy modification.",
                    "At 7 Prowess Passives, Dash Attacks, Heavy and Special Attacks grant an Unblockable Passive for 4 seconds. This Unblockable Passive is paused during Special Attacks and has a 10 second cooldown unless Sauron's Ability Accuracy is being modified or Sauron is affected by a Degeneration.",
                    "At 10 Prowess Passives, Dashing Attacks, inflict a Bleed Passive, dealing +1623 damage over 4 seconds. This ability can also trigger through block.",
                    "Landing the first hit of a Heavy Attack will consume 3 Prowess Passives and gain a Fury Passive, granting +1082 Attack Rating for 4 seconds"
                ],
                "ALL SPECIAL ATTACKS": [
                    "All Prowess Passives are removed at the end of Special Attacks.",
                    "On activation, pause the Degeneration Passive from Extinction Mode for 8 seconds."
                ],
                "EXTINCTION MODE": [
                    "While at 10 Prowess Passives, when you hit the Opponent, inflict a Degeneration Passive, dealing +865.6 direct damage over 5 seconds.",
                    "Increase Physical Burst Potency by 50% and all personal Abilities have 100% Ability Accuracy.",
                    "If the Degeneration Passive from Extinction Mode expires, remove all Prowess Passives."
                ],
                "SPECIAL ATTACK 1": [
                    "After this Special Attack ends, for each physical burst hit dealt to the Opponent, heal for 25% the damage dealt for 10 seconds."
                ],
                "SPECIAL ATTACK 2": [
                    "After this Special Attack ends, increase the Potency of all personal burst Physical Damage by 100% for 10 seconds."
                ],
                "SPECIAL ATTACK 3": [
                    "After this Special Attack ends, inflict a Degeneration Passive, dealing +541 direct damage over 5 seconds per personal Passive effect that has expired on Sauron or on the Opponent. (capped at 30) Reset after Special 3 activation."
                ]
            }
        },
        "6+2": {
            "rank": 2,
            "prestige": "8526",
            "hp": "Offensive: Damage Over Time",
            "attack": "2990",
            "crit_rate": "628",
            "crit_dmge": "738",
            "armor": "431",
            "block_prof": "3734",
            "energy_resist": "0",
            "physical_resist": "0",
            "crit_resist": "0",
            "sig_info": [
                "After the start of the fight, if the Opponent attempts to inflict a Bleed, or Incinerate effect while a Degeneration Passive is active, inflict the Opponent with a Passive version of that effect dealing +8970 damage over 2 seconds.",
                "Increase personal Prowess Passive Potency by a flat 2 to 10%."
            ],
            "url_page": "https://auntm.ai/champions/sauron/tier/6",
            "champid": "sauron+6+2",
            "challenger_rating": 120,
            "abilities": {
                "ALWAYS ACTIVE": [
                    "Immune to all Power Steal, Poison, and Sauron's Regeneration Rate cannot be decreased or increased by outside sources.",
                    "Take -95% less damage from Bleed effects and gain +25% Critical Resistance while Bleeding.",
                    "When Sauron is struck, 30% chance to gain a Regen Passive healing 10% of the damage taken per personal Prowess Passive effect he has.",
                    "Light Attacks have 35% chance to deal 50% of the damage dealt as a burst of Physical Damage. This ability can also trigger through block."
                ],
                "PROWESS (MAX: 10)": [
                    "Each time one of Sauron\u2019s Abilities fails to trigger due to chance gain a 10% Prowess Passive. Gain an additional 2 Prowess Passive if Sauron's Ability fails due to Ability Accuracy modification.",
                    "At 7 Prowess Passives, Dash Attacks, Heavy and Special Attacks grant an Unblockable Passive for 4 seconds. This Unblockable Passive is paused during Special Attacks and has a 10 second cooldown unless Sauron's Ability Accuracy is being modified or Sauron is affected by a Degeneration.",
                    "At 10 Prowess Passives, Dashing Attacks, inflict a Bleed Passive, dealing +2242.5 damage over 4 seconds. This ability can also trigger through block.",
                    "Landing the first hit of a Heavy Attack will consume 3 Prowess Passives and gain a Fury Passive, granting +1495 Attack Rating for 4 seconds"
                ],
                "ALL SPECIAL ATTACKS": [
                    "All Prowess Passives are removed at the end of Special Attacks.",
                    "On activation, pause the Degeneration Passive from Extinction Mode for 8 seconds."
                ],
                "EXTINCTION MODE": [
                    "While at 10 Prowess Passives, when you hit the Opponent, inflict a Degeneration Passive, dealing +1196 direct damage over 5 seconds.",
                    "Increase Physical Burst Potency by 50% and all personal Abilities have 100% Ability Accuracy.",
                    "If the Degeneration Passive from Extinction Mode expires, remove all Prowess Passives."
                ],
                "SPECIAL ATTACK 1": [
                    "After this Special Attack ends, for each physical burst hit dealt to the Opponent, heal for 25% the damage dealt for 10 seconds."
                ],
                "SPECIAL ATTACK 2": [
                    "After this Special Attack ends, increase the Potency of all personal burst Physical Damage by 100% for 10 seconds."
                ],
                "SPECIAL ATTACK 3": [
                    "After this Special Attack ends, inflict a Degeneration Passive, dealing +747.5 direct damage over 5 seconds per personal Passive effect that has expired on Sauron or on the Opponent. (capped at 30) Reset after Special 3 activation."
                ]
            }
        },
        "6+3": {
            "rank": 3,
            "prestige": "10135",
            "hp": "Offensive: Damage Over Time",
            "attack": "3547",
            "crit_rate": "643",
            "crit_dmge": "756",
            "armor": "472",
            "block_prof": "3823",
            "energy_resist": "0",
            "physical_resist": "0",
            "crit_resist": "0",
            "sig_info": [
                "After the start of the fight, if the Opponent attempts to inflict a Bleed, or Incinerate effect while a Degeneration Passive is active, inflict the Opponent with a Passive version of that effect dealing +10641 damage over 2 seconds.",
                "Increase personal Prowess Passive Potency by a flat 2 to 10%."
            ],
            "url_page": "https://auntm.ai/champions/sauron/tier/6",
            "champid": "sauron+6+3",
            "challenger_rating": 130,
            "abilities": {
                "ALWAYS ACTIVE": [
                    "Immune to all Power Steal, Poison, and Sauron's Regeneration Rate cannot be decreased or increased by outside sources.",
                    "Take -95% less damage from Bleed effects and gain +25% Critical Resistance while Bleeding.",
                    "When Sauron is struck, 30% chance to gain a Regen Passive healing 10% of the damage taken per personal Prowess Passive effect he has.",
                    "Light Attacks have 35% chance to deal 50% of the damage dealt as a burst of Physical Damage. This ability can also trigger through block."
                ],
                "PROWESS (MAX: 10)": [
                    "Each time one of Sauron\u2019s Abilities fails to trigger due to chance gain a 10% Prowess Passive. Gain an additional 2 Prowess Passive if Sauron's Ability fails due to Ability Accuracy modification.",
                    "At 7 Prowess Passives, Dash Attacks, Heavy and Special Attacks grant an Unblockable Passive for 4 seconds. This Unblockable Passive is paused during Special Attacks and has a 10 second cooldown unless Sauron's Ability Accuracy is being modified or Sauron is affected by a Degeneration.",
                    "At 10 Prowess Passives, Dashing Attacks, inflict a Bleed Passive, dealing +2660.25 damage over 4 seconds. This ability can also trigger through block.",
                    "Landing the first hit of a Heavy Attack will consume 3 Prowess Passives and gain a Fury Passive, granting +1773.5 Attack Rating for 4 seconds"
                ],
                "ALL SPECIAL ATTACKS": [
                    "All Prowess Passives are removed at the end of Special Attacks.",
                    "On activation, pause the Degeneration Passive from Extinction Mode for 8 seconds."
                ],
                "EXTINCTION MODE": [
                    "While at 10 Prowess Passives, when you hit the Opponent, inflict a Degeneration Passive, dealing +1418.8 direct damage over 5 seconds.",
                    "Increase Physical Burst Potency by 50% and all personal Abilities have 100% Ability Accuracy.",
                    "If the Degeneration Passive from Extinction Mode expires, remove all Prowess Passives."
                ],
                "SPECIAL ATTACK 1": [
                    "After this Special Attack ends, for each physical burst hit dealt to the Opponent, heal for 25% the damage dealt for 10 seconds."
                ],
                "SPECIAL ATTACK 2": [
                    "After this Special Attack ends, increase the Potency of all personal burst Physical Damage by 100% for 10 seconds."
                ],
                "SPECIAL ATTACK 3": [
                    "After this Special Attack ends, inflict a Degeneration Passive, dealing +886.75 direct damage over 5 seconds per personal Passive effect that has expired on Sauron or on the Opponent. (capped at 30) Reset after Special 3 activation."
                ]
            }
        },
        "6+4": {
            "rank": 4,
            "prestige": "11595",
            "hp": "Offensive: Damage Over Time",
            "attack": "4058",
            "crit_rate": "658",
            "crit_dmge": "773",
            "armor": "517",
            "block_prof": "3912",
            "energy_resist": "0",
            "physical_resist": "0",
            "crit_resist": "0",
            "sig_info": [
                "After the start of the fight, if the Opponent attempts to inflict a Bleed, or Incinerate effect while a Degeneration Passive is active, inflict the Opponent with a Passive version of that effect dealing +12174 damage over 2 seconds.",
                "Increase personal Prowess Passive Potency by a flat 2 to 10%."
            ],
            "url_page": "https://auntm.ai/champions/sauron/tier/6",
            "champid": "sauron+6+4",
            "challenger_rating": 140,
            "abilities": {
                "ALWAYS ACTIVE": [
                    "Immune to all Power Steal, Poison, and Sauron's Regeneration Rate cannot be decreased or increased by outside sources.",
                    "Take -95% less damage from Bleed effects and gain +25% Critical Resistance while Bleeding.",
                    "When Sauron is struck, 30% chance to gain a Regen Passive healing 10% of the damage taken per personal Prowess Passive effect he has.",
                    "Light Attacks have 35% chance to deal 50% of the damage dealt as a burst of Physical Damage. This ability can also trigger through block."
                ],
                "PROWESS (MAX: 10)": [
                    "Each time one of Sauron\u2019s Abilities fails to trigger due to chance gain a 10% Prowess Passive. Gain an additional 2 Prowess Passive if Sauron's Ability fails due to Ability Accuracy modification.",
                    "At 7 Prowess Passives, Dash Attacks, Heavy and Special Attacks grant an Unblockable Passive for 4 seconds. This Unblockable Passive is paused during Special Attacks and has a 10 second cooldown unless Sauron's Ability Accuracy is being modified or Sauron is affected by a Degeneration.",
                    "At 10 Prowess Passives, Dashing Attacks, inflict a Bleed Passive, dealing +3043.5 damage over 4 seconds. This ability can also trigger through block.",
                    "Landing the first hit of a Heavy Attack will consume 3 Prowess Passives and gain a Fury Passive, granting +2029 Attack Rating for 4 seconds"
                ],
                "ALL SPECIAL ATTACKS": [
                    "All Prowess Passives are removed at the end of Special Attacks.",
                    "On activation, pause the Degeneration Passive from Extinction Mode for 8 seconds."
                ],
                "EXTINCTION MODE": [
                    "While at 10 Prowess Passives, when you hit the Opponent, inflict a Degeneration Passive, dealing +1623.2 direct damage over 5 seconds.",
                    "Increase Physical Burst Potency by 50% and all personal Abilities have 100% Ability Accuracy.",
                    "If the Degeneration Passive from Extinction Mode expires, remove all Prowess Passives."
                ],
                "SPECIAL ATTACK 1": [
                    "After this Special Attack ends, for each physical burst hit dealt to the Opponent, heal for 25% the damage dealt for 10 seconds."
                ],
                "SPECIAL ATTACK 2": [
                    "After this Special Attack ends, increase the Potency of all personal burst Physical Damage by 100% for 10 seconds."
                ],
                "SPECIAL ATTACK 3": [
                    "After this Special Attack ends, inflict a Degeneration Passive, dealing +1014.5 direct damage over 5 seconds per personal Passive effect that has expired on Sauron or on the Opponent. (capped at 30) Reset after Special 3 activation."
                ]
            }
        },
        "1+1": {
            "rank": 1,
            "prestige": 218,
            "hp": 835,
            "attack": 77,
            "crit_rate": 463,
            "crit_dmge": 545,
            "armor": 0,
            "block_prof": 2756,
            "energy_resist": 0,
            "physical_resist": 0,
            "crit_resist": 0,
            "sig_info": null,
            "url_page": "https://auntm.ai/champions/sauron/tier/1",
            "champid": "sauron+1+1",
            "challenger_rating": 10,
            "abilities": {
                "ALWAYS ACTIVE": [
                    "Immune to all Power Steal, Poison, and Sauron's Regeneration Rate cannot be decreased or increased by outside sources.",
                    "Take -95% less damage from Bleed effects and gain +25% Critical Resistance while Bleeding.",
                    "When Sauron is struck, 30% chance to gain a Regen Passive healing 10% of the damage taken per personal Prowess Passive effect he has.",
                    "Light Attacks have 35% chance to deal 50% of the damage dealt as a burst of Physical Damage. This ability can also trigger through block."
                ],
                "PROWESS (MAX: 10)": [
                    "Each time one of Sauron\u2019s Abilities fails to trigger due to chance gain a 10% Prowess Passive. Gain an additional 2 Prowess Passive if Sauron's Ability fails due to Ability Accuracy modification.",
                    "At 7 Prowess Passives, Dash Attacks, Heavy and Special Attacks grant an Unblockable Passive for 4 seconds. This Unblockable Passive is paused during Special Attacks and has a 10 second cooldown unless Sauron's Ability Accuracy is being modified or Sauron is affected by a Degeneration.",
                    "At 10 Prowess Passives, Dashing Attacks, inflict a Bleed Passive, dealing +57.75 damage over 4 seconds. This ability can also trigger through block.",
                    "Landing the first hit of a Heavy Attack will consume 3 Prowess Passives and gain a Fury Passive, granting +38.5 Attack Rating for 4 seconds"
                ],
                "ALL SPECIAL ATTACKS": [
                    "All Prowess Passives are removed at the end of Special Attacks.",
                    "On activation, pause the Degeneration Passive from Extinction Mode for 8 seconds."
                ],
                "EXTINCTION MODE": [
                    "While at 10 Prowess Passives, when you hit the Opponent, inflict a Degeneration Passive, dealing +30.8 direct damage over 5 seconds.",
                    "Increase Physical Burst Potency by 50% and all personal Abilities have 100% Ability Accuracy.",
                    "If the Degeneration Passive from Extinction Mode expires, remove all Prowess Passives."
                ],
                "SPECIAL ATTACK 1": [
                    "After this Special Attack ends, for each physical burst hit dealt to the Opponent, heal for 25% the damage dealt for 10 seconds."
                ],
                "SPECIAL ATTACK 2": [
                    "After this Special Attack ends, increase the Potency of all personal burst Physical Damage by 100% for 10 seconds."
                ],
                "SPECIAL ATTACK 3": [
                    "After this Special Attack ends, inflict a Degeneration Passive, dealing +19.25 direct damage over 5 seconds per personal Passive effect that has expired on Sauron or on the Opponent. (capped at 30) Reset after Special 3 activation."
                ]
            }
        },
        "1+2": {
            "rank": 2,
            "prestige": 302,
            "hp": 1155,
            "attack": 107,
            "crit_rate": 478,
            "crit_dmge": 563,
            "armor": 0,
            "block_prof": 2845,
            "energy_resist": 0,
            "physical_resist": 0,
            "crit_resist": 0,
            "sig_info": null,
            "url_page": "https://auntm.ai/champions/sauron/tier/1",
            "champid": "sauron+1+2",
            "challenger_rating": 20,
            "abilities": {
                "ALWAYS ACTIVE": [
                    "Immune to all Power Steal, Poison, and Sauron's Regeneration Rate cannot be decreased or increased by outside sources.",
                    "Take -95% less damage from Bleed effects and gain +25% Critical Resistance while Bleeding.",
                    "When Sauron is struck, 30% chance to gain a Regen Passive healing 10% of the damage taken per personal Prowess Passive effect he has.",
                    "Light Attacks have 35% chance to deal 50% of the damage dealt as a burst of Physical Damage. This ability can also trigger through block."
                ],
                "PROWESS (MAX: 10)": [
                    "Each time one of Sauron\u2019s Abilities fails to trigger due to chance gain a 10% Prowess Passive. Gain an additional 2 Prowess Passive if Sauron's Ability fails due to Ability Accuracy modification.",
                    "At 7 Prowess Passives, Dash Attacks, Heavy and Special Attacks grant an Unblockable Passive for 4 seconds. This Unblockable Passive is paused during Special Attacks and has a 10 second cooldown unless Sauron's Ability Accuracy is being modified or Sauron is affected by a Degeneration.",
                    "At 10 Prowess Passives, Dashing Attacks, inflict a Bleed Passive, dealing +80.25 damage over 4 seconds. This ability can also trigger through block.",
                    "Landing the first hit of a Heavy Attack will consume 3 Prowess Passives and gain a Fury Passive, granting +53.5 Attack Rating for 4 seconds"
                ],
                "ALL SPECIAL ATTACKS": [
                    "All Prowess Passives are removed at the end of Special Attacks.",
                    "On activation, pause the Degeneration Passive from Extinction Mode for 8 seconds."
                ],
                "EXTINCTION MODE": [
                    "While at 10 Prowess Passives, when you hit the Opponent, inflict a Degeneration Passive, dealing +42.8 direct damage over 5 seconds.",
                    "Increase Physical Burst Potency by 50% and all personal Abilities have 100% Ability Accuracy.",
                    "If the Degeneration Passive from Extinction Mode expires, remove all Prowess Passives."
                ],
                "SPECIAL ATTACK 1": [
                    "After this Special Attack ends, for each physical burst hit dealt to the Opponent, heal for 25% the damage dealt for 10 seconds."
                ],
                "SPECIAL ATTACK 2": [
                    "After this Special Attack ends, increase the Potency of all personal burst Physical Damage by 100% for 10 seconds."
                ],
                "SPECIAL ATTACK 3": [
                    "After this Special Attack ends, inflict a Degeneration Passive, dealing +26.75 direct damage over 5 seconds per personal Passive effect that has expired on Sauron or on the Opponent. (capped at 30) Reset after Special 3 activation."
                ]
            }
        },
        "find": {
            "story_quests": {
                "act_1": [],
                "act_2": [],
                "act_3": [],
                "act_4": [],
                "act_5": [],
                "act_6": [],
                "act_7": [
                    "7.4.2"
                ]
            }
        }
    },
    "name": "SAURON",
    "class": "Mutant",
    "img_portrait": "https://mcoc.rexians.tk/assets/portraits/sauron.png",
    "contact": "PHYSICAL",
    "tags": [
        "Villain",
        "Size: M"
    ],
    "released": "1/27/2022"
}