{
  "champid": "spiderham",
  "data": {
    "2+1": {
      "rank": 1,
      "prestige": "281",
      "hp": "914",
      "attack": "95",
      "crit_rate": "719",
      "crit_dmge": "825",
      "armor": "67",
      "block_prof": "2401",
      "energy_resist": "0",
      "physical_resist": "219",
      "crit_resist": "0",
      "sig_info": [
        "Whenever Spider-Ham Evades, he places a Porker Popper on the Opponent.",
        "Whenever Spider-Ham is Struck while Stunned, 30% chance to remove 1 Spider-Nonsense and place a non-stacking Porker Popper on the Opponent.",
        "These Porker Poppers last for 7 to 12 second(s) and deal 33.25 Damage.",
        "While Spider-Nonsense is at 10, it lasts for an additional 0.2 to 1.3 second(s) before resetting."
      ],
      "url_page": "https://auntm.ai/champions/spiderham/tier/2",
      "champid": "spiderham+2+1",
      "challenger_rating": 20
    },
    "2+2": {
      "rank": 2,
      "prestige": "371",
      "hp": "1208",
      "attack": "125",
      "crit_rate": "742",
      "crit_dmge": "851",
      "armor": "87",
      "block_prof": "2476",
      "energy_resist": "0",
      "physical_resist": "225",
      "crit_resist": "0",
      "sig_info": [
        "Whenever Spider-Ham Evades, he places a Porker Popper on the Opponent.",
        "Whenever Spider-Ham is Struck while Stunned, 30% chance to remove 1 Spider-Nonsense and place a non-stacking Porker Popper on the Opponent.",
        "These Porker Poppers last for 7 to 12 second(s) and deal 43.75 Damage.",
        "While Spider-Nonsense is at 10, it lasts for an additional 0.2 to 1.3 second(s) before resetting."
      ],
      "url_page": "https://auntm.ai/champions/spiderham/tier/2",
      "champid": "spiderham+2+2",
      "challenger_rating": 30
    },
    "2+3": {
      "rank": 3,
      "prestige": "587",
      "hp": "1917",
      "attack": "198",
      "crit_rate": "764",
      "crit_dmge": "876",
      "armor": "109",
      "block_prof": "2551",
      "energy_resist": "0",
      "physical_resist": "232",
      "crit_resist": "0",
      "sig_info": [
        "Whenever Spider-Ham Evades, he places a Porker Popper on the Opponent.",
        "Whenever Spider-Ham is Struck while Stunned, 30% chance to remove 1 Spider-Nonsense and place a non-stacking Porker Popper on the Opponent.",
        "These Porker Poppers last for 7 to 12 second(s) and deal 69.3 Damage.",
        "While Spider-Nonsense is at 10, it lasts for an additional 0.2 to 1.3 second(s) before resetting."
      ],
      "url_page": "https://auntm.ai/champions/spiderham/tier/2",
      "champid": "spiderham+2+3",
      "challenger_rating": 40
    },
    "3+1": {
      "rank": 1,
      "prestige": "508",
      "hp": "1657",
      "attack": "171",
      "crit_rate": "764",
      "crit_dmge": "876",
      "armor": "71",
      "block_prof": "2551",
      "energy_resist": "0",
      "physical_resist": "232",
      "crit_resist": "0",
      "sig_info": [
        "Whenever Spider-Ham Evades, he places a Porker Popper on the Opponent.",
        "Whenever Spider-Ham is Struck while Stunned, 30% chance to remove 1 Spider-Nonsense and place a non-stacking Porker Popper on the Opponent.",
        "These Porker Poppers last for 7 to 12 second(s) and deal 59.85 Damage.",
        "While Spider-Nonsense is at 10, it lasts for an additional 0.2 to 1.3 second(s) before resetting."
      ],
      "url_page": "https://auntm.ai/champions/spiderham/tier/3",
      "champid": "spiderham+3+1",
      "challenger_rating": 40
    },
    "3+2": {
      "rank": 2,
      "prestige": "815",
      "hp": "2651",
      "attack": "274",
      "crit_rate": "787",
      "crit_dmge": "902",
      "armor": "93",
      "block_prof": "2626",
      "energy_resist": "0",
      "physical_resist": "239",
      "crit_resist": "0",
      "sig_info": [
        "Whenever Spider-Ham Evades, he places a Porker Popper on the Opponent.",
        "Whenever Spider-Ham is Struck while Stunned, 30% chance to remove 1 Spider-Nonsense and place a non-stacking Porker Popper on the Opponent.",
        "These Porker Poppers last for 7 to 12 second(s) and deal 95.9 Damage.",
        "While Spider-Nonsense is at 10, it lasts for an additional 0.2 to 1.3 second(s) before resetting."
      ],
      "url_page": "https://auntm.ai/champions/spiderham/tier/3",
      "champid": "spiderham+3+2",
      "challenger_rating": 50
    },
    "3+3": {
      "rank": 3,
      "prestige": "1138",
      "hp": "3709",
      "attack": "383",
      "crit_rate": "809",
      "crit_dmge": "928",
      "armor": "115",
      "block_prof": "2701",
      "energy_resist": "0",
      "physical_resist": "246",
      "crit_resist": "0",
      "sig_info": [
        "Whenever Spider-Ham Evades, he places a Porker Popper on the Opponent.",
        "Whenever Spider-Ham is Struck while Stunned, 30% chance to remove 1 Spider-Nonsense and place a non-stacking Porker Popper on the Opponent.",
        "These Porker Poppers last for 7 to 12 second(s) and deal 134.05 Damage.",
        "While Spider-Nonsense is at 10, it lasts for an additional 0.2 to 1.3 second(s) before resetting."
      ],
      "url_page": "https://auntm.ai/champions/spiderham/tier/3",
      "champid": "spiderham+3+3",
      "challenger_rating": 60
    },
    "3+4": {
      "rank": 4,
      "prestige": "1561",
      "hp": "5093",
      "attack": "525",
      "crit_rate": "832",
      "crit_dmge": "954",
      "armor": "140",
      "block_prof": "2776",
      "energy_resist": "0",
      "physical_resist": "253",
      "crit_resist": "0",
      "sig_info": [
        "Whenever Spider-Ham Evades, he places a Porker Popper on the Opponent.",
        "Whenever Spider-Ham is Struck while Stunned, 30% chance to remove 1 Spider-Nonsense and place a non-stacking Porker Popper on the Opponent.",
        "These Porker Poppers last for 7 to 12 second(s) and deal 183.75 Damage.",
        "While Spider-Nonsense is at 10, it lasts for an additional 0.2 to 1.3 second(s) before resetting."
      ],
      "url_page": "https://auntm.ai/champions/spiderham/tier/3",
      "champid": "spiderham+3+4",
      "challenger_rating": 70
    },
    "4+1": {
      "rank": 1,
      "prestige": "1139",
      "hp": "3706",
      "attack": "382",
      "crit_rate": "809",
      "crit_dmge": "928",
      "armor": "157",
      "block_prof": "2701",
      "energy_resist": "0",
      "physical_resist": "246",
      "crit_resist": "0",
      "sig_info": [
        "Whenever Spider-Ham Evades, he places a Porker Popper on the Opponent.",
        "Whenever Spider-Ham is Struck while Stunned, 30% chance to remove 1 Spider-Nonsense and place a non-stacking Porker Popper on the Opponent.",
        "These Porker Poppers last for 7 to 12 second(s) and deal 133.7 Damage.",
        "While Spider-Nonsense is at 10, it lasts for an additional 0.2 to 1.3 second(s) before resetting."
      ],
      "url_page": "https://auntm.ai/champions/spiderham/tier/4",
      "champid": "spiderham+4+1",
      "challenger_rating": 60
    },
    "4+2": {
      "rank": 2,
      "prestige": "1597",
      "hp": "5199",
      "attack": "536",
      "crit_rate": "832",
      "crit_dmge": "954",
      "armor": "183",
      "block_prof": "2776",
      "energy_resist": "0",
      "physical_resist": "253",
      "crit_resist": "0",
      "sig_info": [
        "Whenever Spider-Ham Evades, he places a Porker Popper on the Opponent.",
        "Whenever Spider-Ham is Struck while Stunned, 30% chance to remove 1 Spider-Nonsense and place a non-stacking Porker Popper on the Opponent.",
        "These Porker Poppers last for 7 to 12 second(s) and deal 187.6 Damage.",
        "While Spider-Nonsense is at 10, it lasts for an additional 0.2 to 1.3 second(s) before resetting."
      ],
      "url_page": "https://auntm.ai/champions/spiderham/tier/4",
      "champid": "spiderham+4+2",
      "challenger_rating": 70
    },
    "4+3": {
      "rank": 3,
      "prestige": "2238",
      "hp": "7284",
      "attack": "751",
      "crit_rate": "854",
      "crit_dmge": "979",
      "armor": "212",
      "block_prof": "2851",
      "energy_resist": "0",
      "physical_resist": "260",
      "crit_resist": "0",
      "sig_info": [
        "Whenever Spider-Ham Evades, he places a Porker Popper on the Opponent.",
        "Whenever Spider-Ham is Struck while Stunned, 30% chance to remove 1 Spider-Nonsense and place a non-stacking Porker Popper on the Opponent.",
        "These Porker Poppers last for 7 to 12 second(s) and deal 262.85 Damage.",
        "While Spider-Nonsense is at 10, it lasts for an additional 0.2 to 1.3 second(s) before resetting."
      ],
      "url_page": "https://auntm.ai/champions/spiderham/tier/4",
      "champid": "spiderham+4+3",
      "challenger_rating": 80
    },
    "4+4": {
      "rank": 4,
      "prestige": "2945",
      "hp": "9571",
      "attack": "987",
      "crit_rate": "877",
      "crit_dmge": "1005",
      "armor": "242",
      "block_prof": "2926",
      "energy_resist": "0",
      "physical_resist": "266",
      "crit_resist": "0",
      "sig_info": [
        "Whenever Spider-Ham Evades, he places a Porker Popper on the Opponent.",
        "Whenever Spider-Ham is Struck while Stunned, 30% chance to remove 1 Spider-Nonsense and place a non-stacking Porker Popper on the Opponent.",
        "These Porker Poppers last for 7 to 12 second(s) and deal 345.45 Damage.",
        "While Spider-Nonsense is at 10, it lasts for an additional 0.2 to 1.3 second(s) before resetting."
      ],
      "url_page": "https://auntm.ai/champions/spiderham/tier/4",
      "champid": "spiderham+4+4",
      "challenger_rating": 90
    },
    "4+5": {
      "rank": 5,
      "prestige": "3927",
      "hp": "12771",
      "attack": "1317",
      "crit_rate": "899",
      "crit_dmge": "1031",
      "armor": "273",
      "block_prof": "3001",
      "energy_resist": "0",
      "physical_resist": "273",
      "crit_resist": "0",
      "sig_info": [
        "Whenever Spider-Ham Evades, he places a Porker Popper on the Opponent.",
        "Whenever Spider-Ham is Struck while Stunned, 30% chance to remove 1 Spider-Nonsense and place a non-stacking Porker Popper on the Opponent.",
        "These Porker Poppers last for 7 to 12 second(s) and deal 460.95 Damage.",
        "While Spider-Nonsense is at 10, it lasts for an additional 0.2 to 1.3 second(s) before resetting."
      ],
      "url_page": "https://auntm.ai/champions/spiderham/tier/4",
      "champid": "spiderham+4+5",
      "challenger_rating": 100
    },
    "5+1": {
      "rank": 1,
      "prestige": "2350",
      "hp": "7622",
      "attack": "786",
      "crit_rate": "854",
      "crit_dmge": "979",
      "armor": "362",
      "block_prof": "2851",
      "energy_resist": "0",
      "physical_resist": "260",
      "crit_resist": "0",
      "sig_info": [
        "Whenever Spider-Ham Evades, he places a Porker Popper on the Opponent.",
        "Whenever Spider-Ham is Struck while Stunned, 30% chance to remove 1 Spider-Nonsense and place a non-stacking Porker Popper on the Opponent.",
        "These Porker Poppers last for 7 to 14 second(s) and deal 275.1 Damage.",
        "While Spider-Nonsense is at 10, it lasts for an additional 0.2 to 2 second(s) before resetting."
      ],
      "url_page": "https://auntm.ai/champions/spiderham/tier/5",
      "champid": "spiderham+5+1",
      "challenger_rating": 80
    },
    "5+2": {
      "rank": 2,
      "prestige": "3102",
      "hp": "10068",
      "attack": "1038",
      "crit_rate": "877",
      "crit_dmge": "1005",
      "armor": "400",
      "block_prof": "2926",
      "energy_resist": "0",
      "physical_resist": "266",
      "crit_resist": "0",
      "sig_info": [
        "Whenever Spider-Ham Evades, he places a Porker Popper on the Opponent.",
        "Whenever Spider-Ham is Struck while Stunned, 30% chance to remove 1 Spider-Nonsense and place a non-stacking Porker Popper on the Opponent.",
        "These Porker Poppers last for 7 to 14 second(s) and deal 363.3 Damage.",
        "While Spider-Nonsense is at 10, it lasts for an additional 0.2 to 2 second(s) before resetting."
      ],
      "url_page": "https://auntm.ai/champions/spiderham/tier/5",
      "champid": "spiderham+5+2",
      "challenger_rating": 90
    },
    "5+3": {
      "rank": 3,
      "prestige": "4342",
      "hp": "14074",
      "attack": "1451",
      "crit_rate": "899",
      "crit_dmge": "1031",
      "armor": "440",
      "block_prof": "3001",
      "energy_resist": "0",
      "physical_resist": "273",
      "crit_resist": "0",
      "sig_info": [
        "Whenever Spider-Ham Evades, he places a Porker Popper on the Opponent.",
        "Whenever Spider-Ham is Struck while Stunned, 30% chance to remove 1 Spider-Nonsense and place a non-stacking Porker Popper on the Opponent.",
        "These Porker Poppers last for 7 to 14 second(s) and deal 507.85 Damage.",
        "While Spider-Nonsense is at 10, it lasts for an additional 0.2 to 2 second(s) before resetting."
      ],
      "url_page": "https://auntm.ai/champions/spiderham/tier/5",
      "champid": "spiderham+5+3",
      "challenger_rating": 100
    },
    "5+4": {
      "rank": 4,
      "prestige": "5849",
      "hp": "18965",
      "attack": "1955",
      "crit_rate": "922",
      "crit_dmge": "1057",
      "armor": "481",
      "block_prof": "3076",
      "energy_resist": "0",
      "physical_resist": "280",
      "crit_resist": "0",
      "sig_info": [
        "Whenever Spider-Ham Evades, he places a Porker Popper on the Opponent.",
        "Whenever Spider-Ham is Struck while Stunned, 30% chance to remove 1 Spider-Nonsense and place a non-stacking Porker Popper on the Opponent.",
        "These Porker Poppers last for 7 to 14 second(s) and deal 684.25 Damage.",
        "While Spider-Nonsense is at 10, it lasts for an additional 0.2 to 2 second(s) before resetting."
      ],
      "url_page": "https://auntm.ai/champions/spiderham/tier/5",
      "champid": "spiderham+5+4",
      "challenger_rating": 110
    },
    "5+5": {
      "rank": 5,
      "prestige": "7910",
      "hp": "25606",
      "attack": "2640",
      "crit_rate": "944",
      "crit_dmge": "1082",
      "armor": "525",
      "block_prof": "3151",
      "energy_resist": "0",
      "physical_resist": "287",
      "crit_resist": "0",
      "sig_info": [
        "Whenever Spider-Ham Evades, he places a Porker Popper on the Opponent.",
        "Whenever Spider-Ham is Struck while Stunned, 30% chance to remove 1 Spider-Nonsense and place a non-stacking Porker Popper on the Opponent.",
        "These Porker Poppers last for 7 to 14 second(s) and deal 924 Damage.",
        "While Spider-Nonsense is at 10, it lasts for an additional 0.2 to 2 second(s) before resetting."
      ],
      "url_page": "https://auntm.ai/champions/spiderham/tier/5",
      "champid": "spiderham+5+5",
      "challenger_rating": 120
    },
    "6+1": {
      "rank": 1,
      "prestige": "6199",
      "hp": "20135",
      "attack": "2076",
      "crit_rate": "922",
      "crit_dmge": "1057",
      "armor": "391",
      "block_prof": "3076",
      "energy_resist": "0",
      "physical_resist": "280",
      "crit_resist": "0",
      "sig_info": [
        "Whenever Spider-Ham Evades, he places a Porker Popper on the Opponent.",
        "Whenever Spider-Ham is Struck while Stunned, 30% chance to remove 1 Spider-Nonsense and place a non-stacking Porker Popper on the Opponent.",
        "These Porker Poppers last for 7 to 14 second(s) and deal 726.6 Damage.",
        "While Spider-Nonsense is at 10, it lasts for an additional 0.2 to 2 second(s) before resetting."
      ],
      "url_page": "https://auntm.ai/champions/spiderham/tier/6",
      "champid": "spiderham+6+1",
      "challenger_rating": 110
    },
    "6+2": {
      "rank": 2,
      "prestige": "8562",
      "hp": "27812",
      "attack": "2867",
      "crit_rate": "944",
      "crit_dmge": "1082",
      "armor": "431",
      "block_prof": "3151",
      "energy_resist": "0",
      "physical_resist": "287",
      "crit_resist": "0",
      "sig_info": [
        "Whenever Spider-Ham Evades, he places a Porker Popper on the Opponent.",
        "Whenever Spider-Ham is Struck while Stunned, 30% chance to remove 1 Spider-Nonsense and place a non-stacking Porker Popper on the Opponent.",
        "These Porker Poppers last for 7 to 14 second(s) and deal 1003.45 Damage.",
        "While Spider-Nonsense is at 10, it lasts for an additional 0.2 to 2 second(s) before resetting."
      ],
      "url_page": "https://auntm.ai/champions/spiderham/tier/6",
      "champid": "spiderham+6+2",
      "challenger_rating": 120
    },
    "6+3": {
      "rank": 3,
      "prestige": "10174",
      "hp": "32995",
      "attack": "3401",
      "crit_rate": "966",
      "crit_dmge": "1108",
      "armor": "472",
      "block_prof": "3226",
      "energy_resist": "0",
      "physical_resist": "294",
      "crit_resist": "0",
      "sig_info": [
        "Whenever Spider-Ham Evades, he places a Porker Popper on the Opponent.",
        "Whenever Spider-Ham is Struck while Stunned, 30% chance to remove 1 Spider-Nonsense and place a non-stacking Porker Popper on the Opponent.",
        "These Porker Poppers last for 7 to 14 second(s) and deal 1190.35 Damage.",
        "While Spider-Nonsense is at 10, it lasts for an additional 0.2 to 2 second(s) before resetting."
      ],
      "url_page": "https://auntm.ai/champions/spiderham/tier/6",
      "champid": "spiderham+6+3",
      "challenger_rating": 130
    },
    "6+4": {
      "rank": 4,
      "prestige": "11643",
      "hp": "37758",
      "attack": "3892",
      "crit_rate": "989",
      "crit_dmge": "1134",
      "armor": "517",
      "block_prof": "3301",
      "energy_resist": "0",
      "physical_resist": "300",
      "crit_resist": "0",
      "sig_info": [
        "Whenever Spider-Ham Evades, he places a Porker Popper on the Opponent.",
        "Whenever Spider-Ham is Struck while Stunned, 30% chance to remove 1 Spider-Nonsense and place a non-stacking Porker Popper on the Opponent.",
        "These Porker Poppers last for 7 to 14 second(s) and deal 1362.2 Damage.",
        "While Spider-Nonsense is at 10, it lasts for an additional 0.2 to 2 second(s) before resetting."
      ],
      "url_page": "https://auntm.ai/champions/spiderham/tier/6",
      "champid": "spiderham+6+4",
      "challenger_rating": 140
    },
    "1+1": {
      "rank": 1,
      "prestige": 220,
      "hp": 716,
      "attack": 74,
      "crit_rate": 697,
      "crit_dmge": 799,
      "armor": 65,
      "block_prof": 2326,
      "energy_resist": 0,
      "physical_resist": 212,
      "crit_resist": 0,
      "sig_info": null,
      "url_page": "https://auntm.ai/champions/spiderham/tier/1",
      "champid": "spiderham+1+1",
      "challenger_rating": 10
    },
    "1+2": {
      "rank": 2,
      "prestige": 306,
      "hp": 990,
      "attack": 103,
      "crit_rate": 719,
      "crit_dmge": 825,
      "armor": 85,
      "block_prof": 2401,
      "energy_resist": 0,
      "physical_resist": 219,
      "crit_resist": 0,
      "sig_info": null,
      "url_page": "https://auntm.ai/champions/spiderham/tier/1",
      "champid": "spiderham+1+2",
      "challenger_rating": 20
    }
  },
  "name": "SPIDER-HAM",
  "class": "Science",
  "img_portrait": "https://mcoc.rexians.tk/assets/portraits/spiderham.png",
  "contact": "PHYSICAL",
  "tags": [
    "Hero",
    "Size: S"
  ],
  "released": "12/10/2020"
}